README.md
setup.py
lib/__init__.py
lib/basic/__init__.py
lib/basic/index.py
lib/config/__init__.py
lib/config/index.py
lib/main/__init__.py
lib/main/index.py
lib/main/methods.py
lib/tool/__init__.py
lib/tool/dataLegalityChecker.py
lib/tool/initConfig.py
lib/tool/timerRecord.py
lib/worker/__init__.py
lib/worker/index.py
nayo.egg-info/PKG-INFO
nayo.egg-info/SOURCES.txt
nayo.egg-info/dependency_links.txt
nayo.egg-info/requires.txt
nayo.egg-info/top_level.txt